[
  {
    "_id": "6c509d40-5f59-11e7-9349-dd541a093513",
    "_type": "search",
    "_source": {
      "title": "returns",
      "description": "",
      "hits": 0,
      "columns": [
        "_source"
      ],
      "sort": [
        "date_time",
        "desc"
      ],
      "version": 1,
      "kibanaSavedObjectMeta": {
        "searchSourceJSON": "{\n  \"index\": \"geo_weblogs\",\n  \"filter\": [],\n  \"highlight\": {\n    \"pre_tags\": [\n      \"@kibana-highlighted-field@\"\n    ],\n    \"post_tags\": [\n      \"@/kibana-highlighted-field@\"\n    ],\n    \"fields\": {\n      \"*\": {}\n    },\n    \"require_field_match\": false,\n    \"fragment_size\": 2147483647\n  },\n  \"query\": {\n    \"query_string\": {\n      \"query\": \"*\",\n      \"analyze_wildcard\": true\n    }\n  }\n}"
      }
    }
  }
]